{"css_notes_no.1.md":"BYBy6b_Y","css_notes_no.2.md":"Cw7B3mqB","css_notes_no.3.md":"DTGvn7FR","css_notes_no.4.md":"BQYeaTrE","css_notes_no.5.md":"SqfBYXXe","css_notes_no.6.md":"D-mj2Q9w","css_notes_no.7.md":"BrihacnI","css_notes_no.8.md":"BBpTwVvO","css_started.md":"f72bgsmT","html_notes_no.1.md":"Dz_cUrSI","html_notes_no.2.md":"Di-QGaaa","html_notes_no.3.md":"CqMAj4EB","html_started.md":"BkF-IQ_8","http_notes_no.1.md":"CmLFMBIR","http_notes_no.2.md":"DYDLGoVW","http_notes_no.3.md":"BS3GCnK6","http_started.md":"gs4mr6as","index.md":"RN1iEpLJ","javascript_notes_no.1.md":"CNQs3kK5","javascript_notes_no.10.md":"M2JESpT9","javascript_notes_no.11.md":"BP4_PsTE","javascript_notes_no.12.md":"tjveLhy8","javascript_notes_no.13.md":"DrI345h1","javascript_notes_no.2.md":"uUl3JIUW","javascript_notes_no.3.md":"D1BYSl4e","javascript_notes_no.4.md":"DmR8o7VD","javascript_notes_no.5.md":"D2i47uvq","javascript_notes_no.6.md":"CarqTHXO","javascript_notes_no.7.md":"D2Zd4eGZ","javascript_notes_no.8.md":"CngGkHOL","javascript_notes_no.9.md":"Bg3iwQ0o","javascript_started.md":"DpB-X4sj","mobile_notes_no.1.md":"DmgJqPqD","mobile_notes_no.2.md":"Bs2rnO7u","mobile_notes_no.3.md":"C92OKiFC","mobile_notes_no.4.md":"DC9ZydwU","mobile_started.md":"AC80Chq9","plugins_plugin_draggable.md":"DbfP0e-b","plugins_plugin_gaugechart.md":"BkVdP1hD","plugins_plugin_lazyload.md":"BBQ5Nkrb","plugins_plugin_treechart.md":"BGMW9eo1","plugins_started.md":"BUrQXR_4","vue2_notes_no.1.md":"BggZGKZm","vue2_notes_no.2.md":"CmD9yDLa","vue2_notes_no.3.md":"CwSz6VdK","vue2_notes_no.4.md":"cA6Sesxs","vue2_started.md":"bvUzVg7V","vue3_notes_no.1.md":"CG4CGozh","vue3_notes_no.2.md":"D-ehAxeG","vue3_notes_no.3.md":"B1AoEwsV","vue3_started.md":"BK5E0Gvl"}
