{"css_started.md":"Ls5D5zWl","css_no.8.md":"e_18LJrr","html_started.md":"3RAehB2N","css_no.2.md":"oV0uR4GS","index.md":"aDVrqzjo","http_no.2.md":"0mDxzcTI","http_no.3.md":"vvtzDQMw","css_no.7.md":"TLUbP5PZ","html_no.1.md":"JMMJHuT8","http_no.1.md":"IzuwsO2B","javascript_no.5.md":"EE-mVS2y","css_no.4.md":"VGOBN8Ik","javascript_no.10.md":"6VFRHm9z","html_no.2.md":"8yMHV_ih","http_started.md":"iv7gj-yD","javascript_no.6.md":"yFw6jtIe","css_no.5.md":"LYJCSTEA","javascript_no.11.md":"n7njoydm","css_no.3.md":"v8PSQfii","javascript_no.1.md":"wOooKLMi","javascript_started.md":"2joPfPG5","css_no.6.md":"Hm_XYtrs","css_no.1.md":"gAtEzBpA","javascript_no.8.md":"jEsskOqN","javascript_no.7.md":"wnSp73DE","javascript_no.3.md":"AnLfNS5N","javascript_no.4.md":"__BRuB5F","javascript_no.2.md":"uQ88bN3B","javascript_no.9.md":"v6ihhIDi","plugins_started.md":"1hZFQZUZ","plugins_lazyload.md":"xXKu1KQD","plugins_gaugechart.md":"6hT5Lo3L","plugins_treechart.md":"PbKCW13Q","vue2_no.3.md":"uQucW3Qh","vue2_started.md":"gOs15g1D","vue2_no.2.md":"r-cOR4qZ","vue2_no.1.md":"iI5pya8-","vue3_no.2.md":"iQThC2Nn","vue3_started.md":"Od9TFmE3","vue3_no.3.md":"FNA52X-4","vue2_no.4.md":"6j27ry5g","vue3_no.1.md":"RUxc55Wv","plugins_draggable.md":"SCSsN61z"}
